register_8_parallel_in.sv
`default_nettype none


// shift the msb out first
module Register_8_Parallel_In(
    input logic[7:0] parallel_in,
    input logic catch_in,
    input logic en,
    input logic clock,
    output logic output_bit
);

logic[7:0] current_value;

always_ff @( posedge clock ) begin
    if(en) begin
        output_bit <= current_value[7];
        if(catch_in) begin
            current_value <= parallel_in;
            //output_bit <= current_value[7];
        end
        else begin
            current_value <= current_value << 1;
            //output_bit <= current_value[7];
        end
    end
end

endmodule

encoder_8_3.sv
`default_nettype none


module Encoder_8_3(
    input logic en,
    input logic[7:0] in,
    output logic [2:0] out
);

always_comb begin
    if(en) begin
        case(in) 
            128: out = 3'b111;
            64: out = 3'b110;
            32: out = 3'b101;
            16: out = 3'b100;
            8: out = 3'b011;
            4: out = 3'b010;
            2: out = 3'b001;
            1: out = 3'b000;
            default: out = 3'b00;
        endcase
    end
    else begin
        out = 3'b000;
    end
end

endmodule

decoder_3_8.sv
`default_nettype none


module Decoder_3_8(
    input logic en,
    input logic[2:0] in,
    output logic[7:0] out
);

always_comb begin
    if(en) begin
        out = 8'b0;
        out[in] = 1'b1;
    end
    else begin
        out = 8'b000;
    end
end

endmodule

modulo_sm.sv
`default_nettype none


module ModuloDetector (
    input logic input_bit,
    input logic reset,
    input logic clock,
    input logic en,
    output logic [2:0] remainder
);

logic [7:0] internal_buffer;
logic [2:0] next_state_high, next_state_low;

Decoder_3_8 state_decoder(
    .en(1'b1),
    .in(remainder),
    .out(internal_buffer)
);

Encoder_8_3 high_in_encoder(
    .en(input_bit),
    .in({
            1'b0,
            1'b0,
            1'b0,
            internal_buffer[4],
            internal_buffer[1],
            internal_buffer[3],
            internal_buffer[0],
            internal_buffer[2]
        }),
    .out(next_state_high)
);

Encoder_8_3 low_in_encoder(
    .en(~input_bit),
    .in({
            1'b0,
            1'b0,
            1'b0,
            internal_buffer[2],
            internal_buffer[4],
            internal_buffer[1],
            internal_buffer[3],
            internal_buffer[0]
        }),
    .out(next_state_low)
);

always_ff @(posedge clock or posedge reset) begin
    if(en) begin
        if(reset) begin
            remainder <= 3'b000;
        end
        else begin
            if(input_bit == 1'b1) begin
                remainder <= next_state_high;
            end
            else begin
                remainder <= next_state_low;
            end
        end
    end
end


endmodule

test_modulo.sv
`default_nettype none
`include "encoder_8_3.sv"
`include "decoder_3_8.sv"
`include "register_8_parallel_in.sv"

module tb_modulo();

logic[2:0] remainder;
logic reset = 0;
logic clock = 0;
logic input_bit;
logic catch_in = 0;
logic en = 0;
logic en2 = 0;
logic[7:0] input_value = 127;

ModuloDetector dut(
    .input_bit(input_bit),
    .remainder(remainder),
    .en(en2),
    .reset(reset),
    .clock(clock)
);

Register_8_Parallel_In dut2(
    .parallel_in(input_value),
    .catch_in(catch_in),
    .en(en),
    .clock(clock),
    .output_bit(input_bit)
);


initial begin    
    #10 en = 1;
    //for(int x = 0; x < 255; x++) begin
        #10 catch_in = 1;
        #10 clock = 1;
        #10 clock = 0;
        #10 catch_in = 0;
        #10 reset = 1;
        #10 reset = 0;

        #10 clock = 1;
        #10 clock = 0;
        #10 en2 = 1;
        
        for(int x = 0; x < 8; x++) begin 
            #10 clock = 1;
            #10 clock = 0;
            $display ("\n:%0d -> %0d", input_bit, remainder);
        end

        $display ("\n===For the value = %0d, %0d, expected %0d===\n", input_value, remainder, input_value % 5);
    //end
end    

initial begin
    $dumpfile("db_tb_modulo.vcd");
    $dumpvars(1, tb_modulo);
    
end

endmodule

db_tb_modulo.vcd
$date
	Tue Apr  8 23:27:49 2025
$end
$version
	Icarus Verilog
$end
$timescale
	1s
$end
$scope module tb_modulo $end
$var wire 3 ! remainder [2:0] $end
$var wire 1 " input_bit $end
$var reg 1 # catch_in $end
$var reg 1 $ clock $end
$var reg 1 % en $end
$var reg 1 & en2 $end
$var reg 8 ' input_value [7:0] $end
$var reg 1 ( reset $end
$upscope $end
$enddefinitions $end
#0
$dumpvars
0(
b1111111 '
0&
0%
0$
0#
x"
bx !
$end
#10
1%
#20
1#
#30
1$
#40
0$
#50
0#
#60
1(
#70
0(
#80
0"
1$
#90
0$
#100
1&
#110
b0 !
1"
1$
#120
0$
#130
b1 !
1$
#140
0$
#150
b11 !
1$
#160
0$
#170
b10 !
1$
#180
0$
#190
b0 !
1$
#200
0$
#210
b1 !
1$
#220
0$
#230
b11 !
1$
#240
0$
#250
b10 !
0"
1$
